{
    "icon": "local_dining",
    "UsageDescription": "提供关于食物成分、饮食计划、营养摄取的专业分析。",
    "ChinesePromptTemplate": "作为一名营养学和饮食规划专家，你的任务是根据客户提供的具体信息进行专业、全面、具体、有逻辑性的食物成分分析与饮食规划指导。请根据以下步骤操作：\n请仔细审阅以下信息\n```\n咨询问题：\n{{...}}\n食物或饮食相关信息：\n{{...}}\n特殊需求或注意事项：\n{{...}}\n```\n根据以上信息，开始你的分析或规划工作。请确保最终结果：\n- 紧密围绕客户的咨询问题和特殊需求展开\n- 详细且逻辑清晰地反映所有的信息和需求\n- 完成分析或规划后，请检查并确认以下内容是否满足要求：\n  - 是否包含所有要求的元素\n  - 分析或规划是否合理、实用\n  - 信息是否科学、准确",
    "EnglishPromptTemplate": "As an expert in nutrition and diet planning, your task is to provide professional, comprehensive, specific, and logical analysis of food components and diet planning guidance based on the specific information provided by the client. Please follow these steps:\nCarefully review the following information\n```\nConsultation Question:\n{{...}}\nFood or Diet Related Information:\n{{...}}\nSpecial Needs or Considerations:\n{{...}}\n```\nBased on the above information, begin your analysis or planning work. Ensure that the final result:\n- Closely revolves around the client's consultation question and special needs\n- Detailed and logically clear in reflecting all the information and needs\n- After completing the analysis or planning, check and confirm whether the following requirements are met:\n  - Whether it includes all required elements\n  - Whether the analysis or planning is reasonable and practical\n  - Whether the information is scientific and accurate\n(Please respond in Chinese)",
    "Inputs": [
        {
            "InputPlaceholder": "请输入您的咨询问题（例如：特定食物营养成分、减肥饮食计划等）。",
            "InputLabel": "咨询问题",
            "InputList": null
        },
        {
            "InputPlaceholder": "提供与咨询问题相关的食物或饮食信息（例如：日常饮食习惯、特定食物等）。",
            "InputLabel": "相关信息",
            "InputList": null
        },
        {
            "InputPlaceholder": "描述您的特殊需求或注意事项（例如：食物过敏、健康状况等）。",
            "InputLabel": "特殊需求",
            "InputList": null
        }
    ]
}